poxo/__init__.py
poxo/poxo.py
poxo-0.1.0.dist-info/LICENSE
poxo-0.1.0.dist-info/WHEEL
poxo-0.1.0.dist-info/METADATA
poxo-0.1.0.dist-info/RECORD
