Metadata-Version: 2.1
Name: poxo
Version: 0.1.0
Summary: poxo
Home-page: https://github.com/sashakile/poco
Author: sashakile
Author-email: saxa.kile@gmail.com
Requires-Dist: pylint ; extra == "dev"
Requires-Dist: pytest ; extra == "test"
Requires-Dist: pytest-cov ; extra == "test"
Provides-Extra: dev
Provides-Extra: test
